.gitignore
LICENSE
Pipfile
Pipfile.lock
README.md
publish
pyproject.toml
setup.cfg
setup.py
test.sh
djenv/__init__.py
djenv/settings.py
djenv.egg-info/PKG-INFO
djenv.egg-info/SOURCES.txt
djenv.egg-info/dependency_links.txt
djenv.egg-info/requires.txt
djenv.egg-info/top_level.txt
test/__init__.py
test/setup
test/mysite/manage.py
test/mysite/mysite/__init__.py
test/mysite/mysite/asgi.py
test/mysite/mysite/settings.py
test/mysite/mysite/urls.py
test/mysite/mysite/wsgi.py