Metadata-Version: 2.1
Name: djenv
Version: 0.0.6
Summary: DjEnv (Django + Environment): Load Django Settings from Environmental Variables
Home-page: https://github.com/DanielJDufour/djenv
Download-URL: https://github.com/DanielJDufour/djenv/tarball/download
Author: Daniel J. Dufour
Author-email: daniel.j.dufour@gmail.com
Keywords: auto,automate,conf,configure,env,environment,django,loader,settings
Classifier: Development Status :: 5 - Production/Stable
Classifier: Programming Language :: Python :: 3
Classifier: Operating System :: OS Independent
License-File: LICENSE
Requires-Dist: simple-env
